blenv/__init__.py
blenv/__main__.py
blenv-0.0.1b3.dist-info/METADATA
blenv-0.0.1b3.dist-info/WHEEL
blenv-0.0.1b3.dist-info/top_level.txt
blenv-0.0.1b3.dist-info/RECORD
